fastest_asyncapi/__init__.py
fastest_asyncapi/templates/v3/asyncapi.html
fastest_asyncapi/views/__init__.py
fastest_asyncapi/views/async/__init__.py
fastest_asyncapi/views/sync/__init__.py
fastest_asyncapi/views/sync/v3/__init__.py
fastest_asyncapi/views/sync/v3/asyncapi.py
fastapi_asyncapi_docs-0.1.0.dist-info/LICENSE
fastapi_asyncapi_docs-0.1.0.dist-info/METADATA
fastapi_asyncapi_docs-0.1.0.dist-info/WHEEL
fastapi_asyncapi_docs-0.1.0.dist-info/RECORD
