Metadata-Version: 2.1
Name: fastapi-asyncapi-docs
Version: 0.1.0
Summary: 
Author: Sergei Konik
Author-email: s.konik.dev@gmail.com
Requires-Python: >=3.11,<4.0
Classifier: Programming Language :: Python :: 3
Classifier: Programming Language :: Python :: 3.11
Requires-Dist: asyncapi-container (==0.3.0)
Requires-Dist: fastapi (>=0.109.0,<0.110.0)
Requires-Dist: jinja2 (>=3.1.3,<4.0.0)
Requires-Dist: uvicorn (>=0.27.0,<0.28.0)
